setup.py
dsnd_probability_udacity_sahin/Binomialdistribution.py
dsnd_probability_udacity_sahin/Gaussiandistribution.py
dsnd_probability_udacity_sahin/Generaldistribution.py
dsnd_probability_udacity_sahin/__init__.py
dsnd_probability_udacity_sahin.egg-info/PKG-INFO
dsnd_probability_udacity_sahin.egg-info/SOURCES.txt
dsnd_probability_udacity_sahin.egg-info/dependency_links.txt
dsnd_probability_udacity_sahin.egg-info/not-zip-safe
dsnd_probability_udacity_sahin.egg-info/top_level.txt