Metadata-Version: 1.0
Name: dsnd-probability-udacity-sahin
Version: 0.1
Summary: Gaussian distributions
Home-page: UNKNOWN
Author: Ümit Sahin
Author-email: uemitsahin@outlook.de
License: UNKNOWN
Platform: UNKNOWN
